{
  "1128296349566251068": {
    "event": {
      "rollCount": 3,
      "autoSell": true,
      "startTime": 1764654745135,
      "totalFumosRolled": 7400,
      "totalCoinsFromSales": 122350,
      "bestFumo": {
        "name": "OneShotCurse(MYTHICAL)",
        "rarity": "MYTHICAL",
        "picture": "https://animeislandca.com/cdn/shop/files/jujutsu-kaisen-kyurumaru-mahito-big-plush-toy-anime-island-ca.png?v=1692739157&width=1445"
      },
      "bestFumoAt": "12/2/2025, 1:01:37 PM",
      "bestFumoRoll": 2,
      "specialFumoCount": 0,
      "specialFumoFirstAt": null,
      "specialFumoFirstRoll": null,
      "specialFumos": []
    },
    "normal": {
      "rollCount": 1,
      "autoSell": true,
      "startTime": 1764657124116,
      "bestFumo": {
        "name": "DarkYoumu(EXCLUSIVE)",
        "rarity": "EXCLUSIVE",
        "picture": "https://fumo.website/img/918.jpg"
      },
      "bestFumoAt": "12/2/2025, 1:32:04 PM",
      "bestFumoRoll": 1,
      "specialFumoCount": 1,
      "specialFumoFirstAt": "12/2/2025, 1:32:04 PM",
      "specialFumoFirstRoll": 1,
      "lowerSpecialFumos": []
    }
  }
}